gamelib/__init__.py
gamelib/core/__init__.py
gamelib/core/events.py
gamelib/core/gl.py
gamelib/core/input.py
gamelib/core/resources.py
gamelib/core/runtime.py
gamelib/core/time.py
gamelib/core/vectors.py
gamelib/core/window.py
gamelib/ecs/__init__.py
gamelib/ecs/base.py
gamelib/ecs/collisions.py
gamelib/ecs/transforms.py
gamelib/geometry/__init__.py
gamelib/geometry/base.py
gamelib/geometry/collisions.py
gamelib/geometry/cube.py
gamelib/geometry/gridmesh.py
gamelib/geometry/loader.py
gamelib/geometry/transforms.py
gamelib/geometry/wavefront.py
gamelib/rendering/__init__.py
gamelib/rendering/_global.py
gamelib/rendering/buffers.py
gamelib/rendering/camera.py
gamelib/rendering/gpu.py
gamelib/rendering/shaders.py
gamelib/rendering/textures.py
gamelib/rendering/uniforms.py
gamelib/utils/__init__.py
gamelib/utils/ensure.py
gamelib/utils/mark.py
gamelib-0.0.7.dist-info/COPYING
gamelib-0.0.7.dist-info/METADATA
gamelib-0.0.7.dist-info/WHEEL
gamelib-0.0.7.dist-info/top_level.txt
gamelib-0.0.7.dist-info/RECORD
