Metadata-Version: 2.1
Name: gamelib
Version: 0.0.7
Summary: gamelib: A library for creating 3d applications in python.
Home-page: https://github.com/peffjepin/gamelib
Author: Jeffrey Pepin
License: GPL-3.0-or-later
Platform: windows
Platform: linux
Classifier: Programming Language :: Python :: 3
Classifier: Programming Language :: Python :: 3 :: Only
Classifier: Programming Language :: Python :: 3.8
Classifier: Programming Language :: Python :: 3.9
Classifier: Programming Language :: Python :: 3.10
Classifier: License :: OSI Approved :: GNU General Public License v3 or later (GPLv3+)
Requires-Python: >=3.8
License-File: COPYING
Requires-Dist: moderngl (<6.0,>=5.6)
Requires-Dist: moderngl-window (<3.0,>=2.4)
Requires-Dist: numpy (<2.0,>=1.22.0)
Requires-Dist: Pillow (<10,>=9.3.0)
Requires-Dist: pygame (<3.0,>=2.1.0)
Provides-Extra: testing
Requires-Dist: pytest (>=6.0) ; extra == 'testing'
Requires-Dist: pytest-cov (>=2.0) ; extra == 'testing'
Requires-Dist: pytest-mock (>=3.0) ; extra == 'testing'
Requires-Dist: tox (>=3.24) ; extra == 'testing'
